ckanext_hdfs-0.0.1-py2.7-nspkg.pth
ckanext/hdfs/__init__.py
ckanext/hdfs/controller.py
ckanext/hdfs/plugin.py
ckanext/hdfs/uploader.py
ckanext_hdfs-0.0.1.dist-info/LICENSE
ckanext_hdfs-0.0.1.dist-info/METADATA
ckanext_hdfs-0.0.1.dist-info/WHEEL
ckanext_hdfs-0.0.1.dist-info/entry_points.txt
ckanext_hdfs-0.0.1.dist-info/namespace_packages.txt
ckanext_hdfs-0.0.1.dist-info/top_level.txt
ckanext_hdfs-0.0.1.dist-info/RECORD
